[
{
    "language":"English",
    "words":[{"concept":1,
              "text":"mouth"},
             {"concept":2,
              "text":"eye"},
             {"concept":3,
              "text":"ear"},
             {"concept":4,
              "text":"nose"},
             {"concept":5,
              "text":"face"},
             {"concept":6,
              "text":"hand"},
             {"concept":7,
              "text":"foot"},
             {"concept":8,
              "text":"finger"},
             {"concept":9,
              "text":"head"},
             {"concept":10,
              "text":"tooth"}]
},
{
    "language":"Japanese",
    "words":[{"concept":1,
              "text":"くち"},
             {"concept":2,
              "text":"め"},
             {"concept":3,
              "text":"みみ"},
             {"concept":4,
              "text":"はな"},
             {"concept":5,
              "text":"かお"},
             {"concept":6,
              "text":"て"},
             {"concept":7,
              "text":"あし"},
             {"concept":8,
              "text":"ゆび"},
             {"concept":9,
              "text":"あたま"},
             {"concept":10,
              "text":"は"}]
},
{
    "language":"German",
    "words":[{"concept":1,
              "text":"Mund"},
             {"concept":2,
              "text":"Auge"},
             {"concept":3,
              "text":"Ohr"},
             {"concept":4,
              "text":"Nase"},
             {"concept":5,
              "text":"Gesicht"},
             {"concept":6,
              "text":"Hand"},
             {"concept":7,
              "text":"Fuß"},
             {"concept":8,
              "text":"Finger"},
             {"concept":9,
              "text":"Kopf"},
             {"concept":10,
              "text":"Zahn"}]
}
]